{
  "name": "SvcUnit",
  "fields": [
    {
      "fieldName": "name",
      "fieldType": "String",
      "fieldValidateRules": ["required", "minlength", "maxlength"],
      "fieldValidateRulesMinlength": "0",
      "fieldValidateRulesMaxlength": "200"
    },
    {
      "fieldName": "description",
      "fieldType": "String",
      "fieldValidateRules": ["required", "maxlength"],
      "fieldValidateRulesMaxlength": "300"
    }
  ],
  "relationships": [
    {
      "relationshipType": "many-to-one",
      "otherEntityName": "svcGroup",
      "otherEntityRelationshipName": "svcUnit",
      "relationshipName": "group"
    }
  ],
  "javadoc": "Unit entity of SVC.\\n@author KagariV.",
  "entityTableName": "svc_unit",
  "dto": "mapstruct",
  "pagination": "pagination",
  "service": "serviceImpl",
  "jpaMetamodelFiltering": true,
  "fluentMethods": true,
  "readOnly": false,
  "embedded": false,
  "applications": "*",
  "changelogDate": "20210731065411"
}
